{"mang_5":{"data":{"list":[{"type":"head","title":"நம்மாழ்வார்","subTitle":""},{"type":"image","imgurl":"https:\/\/s3.ap-south-1.amazonaws.com\/108dd\/apps_v1\/assets\/alwarsmang\/5.webp","isDrawable":"N","imgCaption":"","fontSize":0,"imgWidth":500,"imgHeight":571,"canResize":"Y","action":{"action":{"actionType":"No","data":[]}}},{"type":"head","title":"திருவாய்மொழி","subTitle":""},{"fontSize":18,"type":"subHead","title":"ஏழாம்பத்து (திருமொழி - 3)","align":"left"},{"type":"horizontalSV","cType":"plainText","style":"normal","desc":"வெள்ளைச் சுரிசங்கொ டாழி யேந்தித் தாமரைக் கண்ணனென் னெஞ்சி னூடே,[NL]புள்ளைக் கடாகின்ற வாற்றைக் காணீர் எஞ்சொல்லிச் சொல்லுகேன் அன்னை மீர்காள்,[NL]வெள்ளச் சுகமவன் வீற்றி ருந்த வேத வொலியும் விழா வொலியும்,[NL]பிள்ளைக் குழாவிளை யாட்டொலி யும் அறாத் திருப்பே ரையில் சேர்வன் நானே.","songNum":"3583"},{"type":"horizontalSV","cType":"plainText","style":"normal","desc":"நானக் கருங்குழல் தோழி மீர்காள்! அன்னை யர்காள்! அயல் சேரியீர்காள்,[NL]நானித் தனிநெஞ்சம் காக்க மாட்டேன் என்வசம் அன்றிதி ராப்ப கல்போய்,[NL]தேன்மொய்த்த பூம்பொழில் தண்ப ணைசூழ் தெந்திருப் பேரையில் வீற்றி ருந்த,[NL]வானப்பி ரான்மணி வண்ணன் கண்ணன் செங்கனி வாயின் திறத்த துவே.","songNum":"3584"},{"type":"horizontalSV","cType":"plainText","style":"normal","desc":"செங்கனி வாயின் திறத்த தாயும் செஞ்சுடர் நீண்முடித் தாழ்ந்த தாயும்,[NL]சங்கொடு சக்கரம் கண்டு கந்தும் தாமரைக் கண்களுக் கற்றுத் தீர்ந்தும்,[NL]திங்களும் நாளும் விழாவ றாத தெந்திருப் பேரையில் வீற்றி ருந்த,[NL]நங்கள் பிரானுக்கென் னெஞ்சம் தோழீ! நாணும் நிரையு மிழந்த துவே!","songNum":"3585"},{"type":"horizontalSV","cType":"plainText","style":"normal","desc":"இழந்தவெம் மாமை திறத்துப் போன என்னெஞ்சி னாருமங் கே ஒழிந்தார்,[NL]உழந்தினி யாரைக்கொண் டெனு சாகோ? ஓதக் கடலொலி போல எங்கும்,[NL]எழுந்தநல் வேதத் தொலிநின் றோங்கு தெந்திருப் பேரையில் வீற்றி ருந்த,[NL]முழங்குசங் கக்கையன் மாயத் தாழ்ந்தேன் அன்னையர் காள்!என்னை யென்மு னிந்தே?","songNum":"3586"},{"type":"horizontalSV","cType":"plainText","style":"normal","desc":"முனிந்து சகடம் உதைத்து மாயப் பேய்முலை யுண்டு மருதி டைப்போய்,[NL]கனிந்த விளவுக்குக் கன்றெ றிந்த கண்ண பிரானுக்கென் பெண்மை தோற்றேன்,[NL]முனிந்தினி யென்செய்தீர் அன்னை மீர்காள். முன்னி யவன்வந்து வீற்றி ருந்த,[NL]கனிந்த பொழில்திருப் பேரை யிற்கே காலம் பெறவென்னைக் காட்டு மினே.","songNum":"3587"},{"type":"horizontalSV","cType":"plainText","style":"normal","desc":"காலம் பெறவென்னைக் காட்டு மின்கள் காதல் கடலின் மிகப் பெரிதால்,[NL]நீல முகில்வண் ணத்தெம் பெருமான் நிற்குமுன் னேவந்தென் கைக்கும் எய்தான்,[NL]ஞாலத் தவன்வந்து வீற்றி ருந்த நான்மறை யாளரும் வேள்வி யோவா,[NL]கோலச் செந்நெற்கள் கவரி வீசும் கூடு புனல்திருப் பேரை யிற்கே.","songNum":"3588"},{"type":"horizontalSV","cType":"plainText","style":"normal","desc":"பேரெயில் சூழ்கடல் தென்னி லங்கை செற்ற பிரான்வந்து வீற்றி ருந்த,[NL]பேரையிற் கேபுக்கென் னெஞ்சம் நாடிப் பேர்த்து வரவெங்கும் காண மாட்டேன்,[NL]ஆரை யினிங் குடையம் தோழி. என்னெஞ்சம் கூவ வல்லாரு மில்லை,[NL]ஆரை யினிக்கொண்டென் சாதிக் கின்றது? என்னெஞ்சம் கண்டது வேகண் டேனே.","songNum":"3589"},{"type":"horizontalSV","cType":"plainText","style":"normal","desc":"கண்டது வேகொண்டெல் லாருங் கூடிக் கார்க்கடல் வண்ணனோ டெந்தி றத்துக்[NL]கொண்டு,அலர் தூற்றிற் றதுமுத லாக் கொண்டவென் காத லுரைக்கில் தோழீ,[NL]மண்டிணி ஞால முமேழ் கடலும் நீள்வி சும்பும் கழியப் பெரிதால்,[NL]தெண்திரை சூழ்ந்தவன் வீற்றி ருந்த தெந்திருப் பேரையில் சேர்வன் சென்றே.","songNum":"3590"},{"type":"horizontalSV","cType":"plainText","style":"normal","desc":"சேர்வஞ்சென் றென்னுடைத் தோழி மீர்காள்! அன்னையர் காள்! என்னைத் தேற்ற வேண்டா,[NL]நீர்கள் உரைக்கின்ற தென்னி தற்கு? நெஞ்சும் நிறைவும் எனக்கிங் கில்லை,[NL]கார்வண்ணன் கார்க்கடல் ஞால முண்ட கண்ண பிரான்வந்து வீற்றி ருந்த,[NL]ஏர்வள வொண்கழ னிப்பழ னத்துத் தென்திருப் பேரை யின்மா நகரே.","songNum":"3591"},{"type":"horizontalSV","cType":"plainText","style":"normal","desc":"நகரமும் நாடும் பிறவும் தேர்வேன் நாணெனக் கில்லையென் தோழி மீர்காள்![NL]சிகரம் அணிநெடு மாடம் நீடு தென்திருப் பேரையில் வீற்றி ருந்த,[NL]மகர நெடுங்குழைக் காதன் மாயன் நூற்றுவ ரையன்று மங்க நூற்ற,[NL]நிகரில் முகில்வண்ணன் நேமி யானென் னெஞ்சம் கவர்ந்தெனை யூழி யானே?","songNum":"3592"},{"type":"horizontalSV","cType":"plainText","style":"normal","desc":"ஊழிதோ றூழி யுருவம் பேரும் செய்கையும் வேறவன் வையங் காக்கும்,[NL]ஆழிநீர் வண்ணனை யச்சு தன்னை அணிகுரு கூர்ச்சட கோபன் சொன்ன,[NL]கேழிலந் தாதியோ ராயி ரத்துள் இவைதிருப் பேரையில் மேய பத்தும்,[NL]ஆழியங் கையனை யேத்த வல்லார் அவரடி மைத்திறத் தாழி யாரே.","songNum":"3593"}]},"share":{"text":"","canShare":"N"}}}